{
  "status": "success",
  "msg": "Successfully fetched data anime quote",
  "data": [
    {
      "categoryId": 8504,
      "id": 26090,
      "username": "@ralex_",
      "fullName": "Robin Alexander",
      "avatar": "https://images.animefansbase.com/avatar/r/ralex_65380.jpg",
      "video": null,
      "image": "https://images.animefansbase.com/artwork/md/2023/10/76554-651bec2b2e315.jpeg",
      "postDate": "2023-10-03 10:25:47",
      "likes": 0,
      "comment": 0,
      "totalRepost": 0,
      "isLiked": false,
      "isRepost": 0,
      "commentPreview": null
    },
    {
      "categoryId": 8503,
      "id": 26087,
      "username": "@ralex_",
      "fullName": "Robin Alexander",
      "avatar": "https://images.animefansbase.com/avatar/r/ralex_65380.jpg",
      "video": null,
      "image": "https://images.animefansbase.com/artwork/md/2023/10/96538-651b208a95364.jpeg",
      "postDate": "2023-10-02 19:56:59",
      "likes": 0,
      "comment": 0,
      "totalRepost": 0,
      "isLiked": false,
      "isRepost": 0,
      "commentPreview": null
    },
    {
      "categoryId": 8502,
      "id": 26083,
      "username": "@ralex_",
      "fullName": "Robin Alexander",
      "avatar": "https://images.animefansbase.com/avatar/r/ralex_65380.jpg",
      "video": null,
      "image": "https://images.animefansbase.com/artwork/md/2023/10/37137-651aa60fa5082.jpeg",
      "postDate": "2023-10-02 11:14:24",
      "likes": 0,
      "comment": 0,
      "totalRepost": 0,
      "isLiked": false,
      "isRepost": 0,
      "commentPreview": null
    },
    {
      "categoryId": 8501,
      "id": 26082,
      "username": "@ralex_",
      "fullName": "Robin Alexander",
      "avatar": "https://images.animefansbase.com/avatar/r/ralex_65380.jpg",
      "video": null,
      "image": "https://images.animefansbase.com/artwork/md/2023/10/79430-651a4fe99801d.jpeg",
      "postDate": "2023-10-02 05:06:50",
      "likes": 1,
      "comment": 0,
      "totalRepost": 0,
      "isLiked": false,
      "isRepost": 0,
      "commentPreview": null
    },
    {
      "categoryId": 8500,
      "id": 26079,
      "username": "@art_lover",
      "fullName": "Jasmine ❤️",
      "avatar": "https://images.animefansbase.com/avatar/r/art_lover3167.jpg",
      "video": null,
      "image": "https://images.animefansbase.com/artwork/md/2023/10/22334-6519869a27fc0.jpeg",
      "postDate": "2023-10-01 14:47:54",
      "likes": 1,
      "comment": 1,
      "totalRepost": 0,
      "isLiked": false,
      "isRepost": 0,
      "commentPreview": {
        "id": "764",
        "image": null,
        "avatar": "nexusxdna74217.jpg",
        "fullName": "Iso",
        "username": "@nexusxdna",
        "postDate": "2023-10-02 11:23:36",
        "commentTxt": "what is the name of This anime?"
      }
    },
    {
      "categoryId": 8499,
      "id": 26071,
      "username": "@ralex_",
      "fullName": "Robin Alexander",
      "avatar": "https://images.animefansbase.com/avatar/r/ralex_65380.jpg",
      "video": null,
      "image": "https://images.animefansbase.com/artwork/md/2023/09/52889-6517bbe7d38cd.jpeg",
      "postDate": "2023-09-30 06:10:48",
      "likes": 0,
      "comment": 0,
      "totalRepost": 0,
      "isLiked": false,
      "isRepost": 0,
      "commentPreview": null
    },
    {
      "categoryId": 8498,
      "id": 26066,
      "username": "@art_lover",
      "fullName": "Jasmine ❤️",
      "avatar": "https://images.animefansbase.com/avatar/r/art_lover3167.jpg",
      "video": null,
      "image": "https://images.animefansbase.com/artwork/md/2023/09/11898-6516ddbe0fdc4.jpeg",
      "postDate": "2023-09-29 14:22:54",
      "likes": 0,
      "comment": 0,
      "totalRepost": 0,
      "isLiked": false,
      "isRepost": 0,
      "commentPreview": null
    },
    {
      "categoryId": 8497,
      "id": 26064,
      "username": "@manjiroosano11",
      "fullName": "Miki Tamara",
      "avatar": "https://images.animefansbase.com/avatar/r/manjiroosano112542.jpg",
      "video": null,
      "image": "https://images.animefansbase.com/artwork/md/2023/09/98685-6516b6c981e90.jpeg",
      "postDate": "2023-09-29 11:36:41",
      "likes": 4,
      "comment": 1,
      "totalRepost": 0,
      "isLiked": false,
      "isRepost": 0,
      "commentPreview": {
        "id": "759",
        "image": "2023/09/40024-6516dafdbaae2.gif",
        "avatar": "art_lover3167.jpg",
        "fullName": "Jasmine ❤️",
        "username": "@art_lover",
        "postDate": "2023-09-29 14:11:09",
        "commentTxt": "😍😍💕💕"
      }
    },
    {
      "categoryId": 8496,
      "id": 26063,
      "username": "@ralex_",
      "fullName": "Robin Alexander",
      "avatar": "https://images.animefansbase.com/avatar/r/ralex_65380.jpg",
      "video": null,
      "image": "https://images.animefansbase.com/artwork/md/2023/09/46814-651699ab536df.jpeg",
      "postDate": "2023-09-29 09:32:27",
      "likes": 1,
      "comment": 0,
      "totalRepost": 0,
      "isLiked": false,
      "isRepost": 0,
      "commentPreview": null
    },
    {
      "categoryId": 8495,
      "id": 26058,
      "username": "@art_lover",
      "fullName": "Jasmine ❤️",
      "avatar": "https://images.animefansbase.com/avatar/r/art_lover3167.jpg",
      "video": null,
      "image": "https://images.animefansbase.com/artwork/md/2023/09/80565-651630496c34e.jpeg",
      "postDate": "2023-09-29 02:02:49",
      "likes": 0,
      "comment": 0,
      "totalRepost": 0,
      "isLiked": false,
      "isRepost": 0,
      "commentPreview": null
    },
    {
      "categoryId": 8494,
      "id": 26054,
      "username": "@ralex_",
      "fullName": "Robin Alexander",
      "avatar": "https://images.animefansbase.com/avatar/r/ralex_65380.jpg",
      "video": null,
      "image": "https://images.animefansbase.com/artwork/md/2023/09/22457-651592c5136e9.jpeg",
      "postDate": "2023-09-28 14:50:45",
      "likes": 0,
      "comment": 0,
      "totalRepost": 0,
      "isLiked": false,
      "isRepost": 0,
      "commentPreview": null
    },
    {
      "categoryId": 8493,
      "id": 26052,
      "username": "@art_lover",
      "fullName": "Jasmine ❤️",
      "avatar": "https://images.animefansbase.com/avatar/r/art_lover3167.jpg",
      "video": null,
      "image": "https://images.animefansbase.com/artwork/md/2023/09/56137-6515409762b29.jpg",
      "postDate": "2023-09-28 09:00:08",
      "likes": 0,
      "comment": 0,
      "totalRepost": 0,
      "isLiked": false,
      "isRepost": 0,
      "commentPreview": null
    },
    {
      "categoryId": 8492,
      "id": 26051,
      "username": "@ralex_",
      "fullName": "Robin Alexander",
      "avatar": "https://images.animefansbase.com/avatar/r/ralex_65380.jpg",
      "video": null,
      "image": "https://images.animefansbase.com/artwork/md/2023/09/66371-6514dae4eed76.jpeg",
      "postDate": "2023-09-28 01:46:13",
      "likes": 0,
      "comment": 0,
      "totalRepost": 0,
      "isLiked": false,
      "isRepost": 0,
      "commentPreview": null
    },
    {
      "categoryId": 8491,
      "id": 26048,
      "username": "@art_lover",
      "fullName": "Jasmine ❤️",
      "avatar": "https://images.animefansbase.com/avatar/r/art_lover3167.jpg",
      "video": null,
      "image": "https://images.animefansbase.com/artwork/md/2023/09/81597-651456893f35c.jpeg",
      "postDate": "2023-09-27 16:21:29",
      "likes": 0,
      "comment": 0,
      "totalRepost": 0,
      "isLiked": false,
      "isRepost": 0,
      "commentPreview": null
    },
    {
      "categoryId": 8490,
      "id": 26045,
      "username": "@ralex_",
      "fullName": "Robin Alexander",
      "avatar": "https://images.animefansbase.com/avatar/r/ralex_65380.jpg",
      "video": null,
      "image": "https://images.animefansbase.com/artwork/md/2023/09/56687-6513f24f5ab80.jpeg",
      "postDate": "2023-09-27 09:13:52",
      "likes": 0,
      "comment": 0,
      "totalRepost": 0,
      "isLiked": false,
      "isRepost": 0,
      "commentPreview": null
    },
    {
      "categoryId": 8489,
      "id": 26042,
      "username": "@art_lover",
      "fullName": "Jasmine ❤️",
      "avatar": "https://images.animefansbase.com/avatar/r/art_lover3167.jpg",
      "video": null,
      "image": "https://images.animefansbase.com/artwork/md/2023/09/94388-6513b55d3977c.jpeg",
      "postDate": "2023-09-27 04:53:49",
      "likes": 0,
      "comment": 0,
      "totalRepost": 0,
      "isLiked": false,
      "isRepost": 0,
      "commentPreview": null
    },
    {
      "categoryId": 8488,
      "id": 26041,
      "username": "@ralex_",
      "fullName": "Robin Alexander",
      "avatar": "https://images.animefansbase.com/avatar/r/ralex_65380.jpg",
      "video": null,
      "image": "https://images.animefansbase.com/artwork/md/2023/09/66467-651393e4afbb7.jpeg",
      "postDate": "2023-09-27 02:31:01",
      "likes": 0,
      "comment": 0,
      "totalRepost": 0,
      "isLiked": false,
      "isRepost": 0,
      "commentPreview": null
    },
    {
      "categoryId": 8487,
      "id": 26039,
      "username": "@art_lover",
      "fullName": "Jasmine ❤️",
      "avatar": "https://images.animefansbase.com/avatar/r/art_lover3167.jpg",
      "video": null,
      "image": "https://images.animefansbase.com/artwork/md/2023/09/26757-65130c885c1e6.jpeg",
      "postDate": "2023-09-26 16:53:28",
      "likes": 0,
      "comment": 0,
      "totalRepost": 0,
      "isLiked": false,
      "isRepost": 0,
      "commentPreview": null
    },
    {
      "categoryId": 8486,
      "id": 26037,
      "username": "@ralex_",
      "fullName": "Robin Alexander",
      "avatar": "https://images.animefansbase.com/avatar/r/ralex_65380.jpg",
      "video": null,
      "image": "https://images.animefansbase.com/artwork/md/2023/09/89518-6512a79304504.jpeg",
      "postDate": "2023-09-26 09:42:43",
      "likes": 0,
      "comment": 0,
      "totalRepost": 0,
      "isLiked": false,
      "isRepost": 0,
      "commentPreview": null
    },
    {
      "categoryId": 8485,
      "id": 26035,
      "username": "@art_lover",
      "fullName": "Jasmine ❤️",
      "avatar": "https://images.animefansbase.com/avatar/r/art_lover3167.jpg",
      "video": null,
      "image": "https://images.animefansbase.com/artwork/md/2023/09/92651-65126f00f2ca1.jpeg",
      "postDate": "2023-09-26 05:41:21",
      "likes": 0,
      "comment": 0,
      "totalRepost": 0,
      "isLiked": false,
      "isRepost": 0,
      "commentPreview": null
    },
    {
      "categoryId": 8484,
      "id": 26031,
      "username": "@ralex_",
      "fullName": "Robin Alexander",
      "avatar": "https://images.animefansbase.com/avatar/r/ralex_65380.jpg",
      "video": null,
      "image": "https://images.animefansbase.com/artwork/md/2023/09/81933-6511c86221916.jpeg",
      "postDate": "2023-09-25 17:50:26",
      "likes": 1,
      "comment": 0,
      "totalRepost": 0,
      "isLiked": false,
      "isRepost": 0,
      "commentPreview": null
    },
    {
      "categoryId": 8483,
      "id": 26025,
      "username": "@ralex_",
      "fullName": "Robin Alexander",
      "avatar": "https://images.animefansbase.com/avatar/r/ralex_65380.jpg",
      "video": null,
      "image": "https://images.animefansbase.com/artwork/md/2023/09/92654-6511484025dfa.jpeg",
      "postDate": "2023-09-25 08:43:44",
      "likes": 1,
      "comment": 0,
      "totalRepost": 0,
      "isLiked": false,
      "isRepost": 0,
      "commentPreview": null
    },
    {
      "categoryId": 8482,
      "id": 26023,
      "username": "@art_lover",
      "fullName": "Jasmine ❤️",
      "avatar": "https://images.animefansbase.com/avatar/r/art_lover3167.jpg",
      "video": null,
      "image": "https://images.animefansbase.com/artwork/md/2023/09/50840-65111170ea317.jpeg",
      "postDate": "2023-09-25 04:49:53",
      "likes": 0,
      "comment": 0,
      "totalRepost": 0,
      "isLiked": false,
      "isRepost": 0,
      "commentPreview": null
    },
    {
      "categoryId": 8481,
      "id": 26016,
      "username": "@manjiroosano11",
      "fullName": "Miki Tamara",
      "avatar": "https://images.animefansbase.com/avatar/r/manjiroosano112542.jpg",
      "video": null,
      "image": "https://images.animefansbase.com/artwork/md/2023/09/15793-6510368721ff2.jpeg",
      "postDate": "2023-09-24 13:15:51",
      "likes": 5,
      "comment": 0,
      "totalRepost": 0,
      "isLiked": false,
      "isRepost": 0,
      "commentPreview": null
    },
    {
      "categoryId": 8480,
      "id": 26015,
      "username": "@art_lover",
      "fullName": "Jasmine ❤️",
      "avatar": "https://images.animefansbase.com/avatar/r/art_lover3167.jpg",
      "video": null,
      "image": "https://images.animefansbase.com/artwork/md/2023/09/58190-65102b08d7f7b.jpeg",
      "postDate": "2023-09-24 12:26:49",
      "likes": 0,
      "comment": 0,
      "totalRepost": 0,
      "isLiked": false,
      "isRepost": 0,
      "commentPreview": null
    },
    {
      "categoryId": 8479,
      "id": 26013,
      "username": "@ralex_",
      "fullName": "Robin Alexander",
      "avatar": "https://images.animefansbase.com/avatar/r/ralex_65380.jpg",
      "video": null,
      "image": "https://images.animefansbase.com/artwork/md/2023/09/10166-650febae534f5.jpg",
      "postDate": "2023-09-24 07:56:30",
      "likes": 1,
      "comment": 0,
      "totalRepost": 0,
      "isLiked": false,
      "isRepost": 0,
      "commentPreview": null
    },
    {
      "categoryId": 8478,
      "id": 26012,
      "username": "@art_lover",
      "fullName": "Jasmine ❤️",
      "avatar": "https://images.animefansbase.com/avatar/r/art_lover3167.jpg",
      "video": null,
      "image": "https://images.animefansbase.com/artwork/md/2023/09/19304-650fca3e3638e.jpeg",
      "postDate": "2023-09-24 05:33:50",
      "likes": 0,
      "comment": 0,
      "totalRepost": 0,
      "isLiked": false,
      "isRepost": 0,
      "commentPreview": null
    },
    {
      "categoryId": 8477,
      "id": 26007,
      "username": "@ralex_",
      "fullName": "Robin Alexander",
      "avatar": "https://images.animefansbase.com/avatar/r/ralex_65380.jpg",
      "video": null,
      "image": "https://images.animefansbase.com/artwork/md/2023/09/6858-650f21762bf75.jpeg",
      "postDate": "2023-09-23 17:33:42",
      "likes": 0,
      "comment": 0,
      "totalRepost": 0,
      "isLiked": false,
      "isRepost": 0,
      "commentPreview": null
    },
    {
      "categoryId": 8476,
      "id": 26005,
      "username": "@art_lover",
      "fullName": "Jasmine ❤️",
      "avatar": "https://images.animefansbase.com/avatar/r/art_lover3167.jpg",
      "video": null,
      "image": "https://images.animefansbase.com/artwork/md/2023/09/60688-650eeab6bd683.jpeg",
      "postDate": "2023-09-23 13:40:07",
      "likes": 1,
      "comment": 0,
      "totalRepost": 0,
      "isLiked": false,
      "isRepost": 0,
      "commentPreview": null
    },
    {
      "categoryId": 8475,
      "id": 26003,
      "username": "@ralex_",
      "fullName": "Robin Alexander",
      "avatar": "https://images.animefansbase.com/avatar/r/ralex_65380.jpg",
      "video": null,
      "image": "https://images.animefansbase.com/artwork/md/2023/09/44190-650eb9ec837d6.jpeg",
      "postDate": "2023-09-23 10:11:57",
      "likes": 0,
      "comment": 0,
      "totalRepost": 0,
      "isLiked": false,
      "isRepost": 0,
      "commentPreview": null
    },
    {
      "categoryId": 8474,
      "id": 26001,
      "username": "@art_lover",
      "fullName": "Jasmine ❤️",
      "avatar": "https://images.animefansbase.com/avatar/r/art_lover3167.jpg",
      "video": null,
      "image": "https://images.animefansbase.com/artwork/md/2023/09/94215-650e64efeb38a.jpeg",
      "postDate": "2023-09-23 04:09:20",
      "likes": 0,
      "comment": 0,
      "totalRepost": 0,
      "isLiked": false,
      "isRepost": 0,
      "commentPreview": null
    },
    {
      "categoryId": 8473,
      "id": 25997,
      "username": "@ralex_",
      "fullName": "Robin Alexander",
      "avatar": "https://images.animefansbase.com/avatar/r/ralex_65380.jpg",
      "video": null,
      "image": "https://images.animefansbase.com/artwork/md/2023/09/99004-650dd24423330.jpeg",
      "postDate": "2023-09-22 17:43:32",
      "likes": 1,
      "comment": 0,
      "totalRepost": 0,
      "isLiked": false,
      "isRepost": 0,
      "commentPreview": null
    },
    {
      "categoryId": 8472,
      "id": 25994,
      "username": "@ralex_",
      "fullName": "Robin Alexander",
      "avatar": "https://images.animefansbase.com/avatar/r/ralex_65380.jpg",
      "video": null,
      "image": "https://images.animefansbase.com/artwork/md/2023/09/52211-650d8df9dfd30.jpeg",
      "postDate": "2023-09-22 12:52:10",
      "likes": 1,
      "comment": 0,
      "totalRepost": 0,
      "isLiked": false,
      "isRepost": 0,
      "commentPreview": null
    },
    {
      "categoryId": 8471,
      "id": 25991,
      "username": "@art_lover",
      "fullName": "Jasmine ❤️",
      "avatar": "https://images.animefansbase.com/avatar/r/art_lover3167.jpg",
      "video": null,
      "image": "https://images.animefansbase.com/artwork/md/2023/09/93527-650d1b523199d.jpeg",
      "postDate": "2023-09-22 04:42:58",
      "likes": 0,
      "comment": 0,
      "totalRepost": 0,
      "isLiked": false,
      "isRepost": 0,
      "commentPreview": null
    },
    {
      "categoryId": 8470,
      "id": 25990,
      "username": "@ralex_",
      "fullName": "Robin Alexander",
      "avatar": "https://images.animefansbase.com/avatar/r/ralex_65380.jpg",
      "video": null,
      "image": "https://images.animefansbase.com/artwork/md/2023/09/33347-650cf05a1a2e8.jpg",
      "postDate": "2023-09-22 01:39:38",
      "likes": 1,
      "comment": 0,
      "totalRepost": 0,
      "isLiked": false,
      "isRepost": 0,
      "commentPreview": null
    },
    {
      "categoryId": 8469,
      "id": 25984,
      "username": "@art_lover",
      "fullName": "Jasmine ❤️",
      "avatar": "https://images.animefansbase.com/avatar/r/art_lover3167.jpg",
      "video": null,
      "image": "https://images.animefansbase.com/artwork/md/2023/09/8740-650c3d099bc12.jpeg",
      "postDate": "2023-09-21 12:54:33",
      "likes": 1,
      "comment": 0,
      "totalRepost": 0,
      "isLiked": false,
      "isRepost": 0,
      "commentPreview": null
    },
    {
      "categoryId": 8468,
      "id": 25981,
      "username": "@ralex_",
      "fullName": "Robin Alexander",
      "avatar": "https://images.animefansbase.com/avatar/r/ralex_65380.jpg",
      "video": null,
      "image": "https://images.animefansbase.com/artwork/md/2023/09/38640-650bef70c0370.jpeg",
      "postDate": "2023-09-21 07:23:29",
      "likes": 1,
      "comment": 0,
      "totalRepost": 0,
      "isLiked": false,
      "isRepost": 0,
      "commentPreview": null
    },
    {
      "categoryId": 8467,
      "id": 25977,
      "username": "@ralex_",
      "fullName": "Robin Alexander",
      "avatar": "https://images.animefansbase.com/avatar/r/ralex_65380.jpg",
      "video": null,
      "image": "https://images.animefansbase.com/artwork/md/2023/09/55401-650b9a2fa97ef.jpeg",
      "postDate": "2023-09-21 01:19:43",
      "likes": 0,
      "comment": 0,
      "totalRepost": 0,
      "isLiked": false,
      "isRepost": 0,
      "commentPreview": null
    },
    {
      "categoryId": 8466,
      "id": 25976,
      "username": "@art_lover",
      "fullName": "Jasmine ❤️",
      "avatar": "https://images.animefansbase.com/avatar/r/art_lover3167.jpg",
      "video": null,
      "image": "https://images.animefansbase.com/artwork/md/2023/09/90398-650b2867e2e54.jpeg",
      "postDate": "2023-09-20 17:14:16",
      "likes": 1,
      "comment": 0,
      "totalRepost": 0,
      "isLiked": false,
      "isRepost": 0,
      "commentPreview": null
    },
    {
      "categoryId": 8465,
      "id": 25974,
      "username": "@ralex_",
      "fullName": "Robin Alexander",
      "avatar": "https://images.animefansbase.com/avatar/r/ralex_65380.jpg",
      "video": null,
      "image": "https://images.animefansbase.com/artwork/md/2023/09/5236-650ad5acda6b8.jpg",
      "postDate": "2023-09-20 11:21:17",
      "likes": 0,
      "comment": 0,
      "totalRepost": 0,
      "isLiked": false,
      "isRepost": 0,
      "commentPreview": null
    },
    {
      "categoryId": 8464,
      "id": 25972,
      "username": "@art_lover",
      "fullName": "Jasmine ❤️",
      "avatar": "https://images.animefansbase.com/avatar/r/art_lover3167.jpg",
      "video": null,
      "image": "https://images.animefansbase.com/artwork/md/2023/09/4285-650a8462464cd.jpeg",
      "postDate": "2023-09-20 05:34:26",
      "likes": 0,
      "comment": 0,
      "totalRepost": 0,
      "isLiked": false,
      "isRepost": 0,
      "commentPreview": null
    },
    {
      "categoryId": 8463,
      "id": 25967,
      "username": "@art_lover",
      "fullName": "Jasmine ❤️",
      "avatar": "https://images.animefansbase.com/avatar/r/art_lover3167.jpg",
      "video": null,
      "image": "https://images.animefansbase.com/artwork/md/2023/09/45126-6509c79b4d697.jpg",
      "postDate": "2023-09-19 16:08:59",
      "likes": 0,
      "comment": 0,
      "totalRepost": 0,
      "isLiked": false,
      "isRepost": 0,
      "commentPreview": null
    },
    {
      "categoryId": 8462,
      "id": 25963,
      "username": "@ralex_",
      "fullName": "Robin Alexander",
      "avatar": "https://images.animefansbase.com/avatar/r/ralex_65380.jpg",
      "video": null,
      "image": "https://images.animefansbase.com/artwork/md/2023/09/1781-650976a168d64.jpeg",
      "postDate": "2023-09-19 10:23:29",
      "likes": 0,
      "comment": 0,
      "totalRepost": 0,
      "isLiked": false,
      "isRepost": 0,
      "commentPreview": null
    },
    {
      "categoryId": 8461,
      "id": 25961,
      "username": "@art_lover",
      "fullName": "Jasmine ❤️",
      "avatar": "https://images.animefansbase.com/avatar/r/art_lover3167.jpg",
      "video": null,
      "image": "https://images.animefansbase.com/artwork/md/2023/09/79602-650946030c8c5.jpeg",
      "postDate": "2023-09-19 06:56:03",
      "likes": 0,
      "comment": 0,
      "totalRepost": 0,
      "isLiked": false,
      "isRepost": 0,
      "commentPreview": null
    },
    {
      "categoryId": 8460,
      "id": 25959,
      "username": "@ralex_",
      "fullName": "Robin Alexander",
      "avatar": "https://images.animefansbase.com/avatar/r/ralex_65380.jpg",
      "video": null,
      "image": "https://images.animefansbase.com/artwork/md/2023/09/47786-650901d3d9a97.jpeg",
      "postDate": "2023-09-19 02:05:08",
      "likes": 0,
      "comment": 0,
      "totalRepost": 0,
      "isLiked": false,
      "isRepost": 0,
      "commentPreview": null
    },
    {
      "categoryId": 8459,
      "id": 25957,
      "username": "@art_lover",
      "fullName": "Jasmine ❤️",
      "avatar": "https://images.animefansbase.com/avatar/r/art_lover3167.jpg",
      "video": null,
      "image": "https://images.animefansbase.com/artwork/md/2023/09/92179-6508889b41711.jpeg",
      "postDate": "2023-09-18 17:27:55",
      "likes": 0,
      "comment": 0,
      "totalRepost": 0,
      "isLiked": false,
      "isRepost": 0,
      "commentPreview": null
    },
    {
      "categoryId": 8458,
      "id": 25952,
      "username": "@ralex_",
      "fullName": "Robin Alexander",
      "avatar": "https://images.animefansbase.com/avatar/r/ralex_65380.jpg",
      "video": null,
      "image": "https://images.animefansbase.com/artwork/md/2023/09/45362-65081c30f2637.jpeg",
      "postDate": "2023-09-18 09:45:21",
      "likes": 0,
      "comment": 0,
      "totalRepost": 0,
      "isLiked": false,
      "isRepost": 0,
      "commentPreview": null
    },
    {
      "categoryId": 8457,
      "id": 25949,
      "username": "@art_lover",
      "fullName": "Jasmine ❤️",
      "avatar": "https://images.animefansbase.com/avatar/r/art_lover3167.jpg",
      "video": null,
      "image": "https://images.animefansbase.com/artwork/md/2023/09/52227-6507f0aed7fd3.jpeg",
      "postDate": "2023-09-18 06:39:43",
      "likes": 0,
      "comment": 0,
      "totalRepost": 0,
      "isLiked": false,
      "isRepost": 0,
      "commentPreview": null
    },
    {
      "categoryId": 8456,
      "id": 25939,
      "username": "@art_lover",
      "fullName": "Jasmine ❤️",
      "avatar": "https://images.animefansbase.com/avatar/r/art_lover3167.jpg",
      "video": null,
      "image": "https://images.animefansbase.com/artwork/md/2023/09/40739-65072f846e3d5.jpeg",
      "postDate": "2023-09-17 16:55:32",
      "likes": 0,
      "comment": 0,
      "totalRepost": 0,
      "isLiked": false,
      "isRepost": 0,
      "commentPreview": null
    },
    {
      "categoryId": 8455,
      "id": 25936,
      "username": "@ralex_",
      "fullName": "Robin Alexander",
      "avatar": "https://images.animefansbase.com/avatar/r/ralex_65380.jpg",
      "video": null,
      "image": "https://images.animefansbase.com/artwork/md/2023/09/2295-6506cc8901aca.jpeg",
      "postDate": "2023-09-17 09:53:13",
      "likes": 0,
      "comment": 0,
      "totalRepost": 0,
      "isLiked": false,
      "isRepost": 0,
      "commentPreview": null
    },
    {
      "categoryId": 8454,
      "id": 25935,
      "username": "@art_lover",
      "fullName": "Jasmine ❤️",
      "avatar": "https://images.animefansbase.com/avatar/r/art_lover3167.jpg",
      "video": null,
      "image": "https://images.animefansbase.com/artwork/md/2023/09/43755-6506a323625e4.jpg",
      "postDate": "2023-09-17 06:56:35",
      "likes": 0,
      "comment": 0,
      "totalRepost": 0,
      "isLiked": false,
      "isRepost": 0,
      "commentPreview": null
    },
    {
      "categoryId": 8453,
      "id": 25925,
      "username": "@animelover",
      "fullName": "Animelover",
      "avatar": "https://images.animefansbase.com/avatar/r/animelover7816.jpg",
      "video": null,
      "image": "https://images.animefansbase.com/artwork/md/2023/09/96498-6505e9ee932a4.jpeg",
      "postDate": "2023-09-16 17:46:22",
      "likes": 0,
      "comment": 0,
      "totalRepost": 0,
      "isLiked": false,
      "isRepost": 0,
      "commentPreview": null
    },
    {
      "categoryId": 8452,
      "id": 25921,
      "username": "@art_lover",
      "fullName": "Jasmine ❤️",
      "avatar": "https://images.animefansbase.com/avatar/r/art_lover3167.jpg",
      "video": null,
      "image": "https://images.animefansbase.com/artwork/md/2023/09/92772-6505d0c6d7c58.jpeg",
      "postDate": "2023-09-16 15:59:03",
      "likes": 0,
      "comment": 0,
      "totalRepost": 0,
      "isLiked": false,
      "isRepost": 0,
      "commentPreview": null
    },
    {
      "categoryId": 8451,
      "id": 25915,
      "username": "@ralex_",
      "fullName": "Robin Alexander",
      "avatar": "https://images.animefansbase.com/avatar/r/ralex_65380.jpg",
      "video": null,
      "image": "https://images.animefansbase.com/artwork/md/2023/09/60843-650583cce2c15.jpg",
      "postDate": "2023-09-16 10:30:37",
      "likes": 0,
      "comment": 0,
      "totalRepost": 0,
      "isLiked": false,
      "isRepost": 0,
      "commentPreview": null
    },
    {
      "categoryId": 8450,
      "id": 25914,
      "username": "@art_lover",
      "fullName": "Jasmine ❤️",
      "avatar": "https://images.animefansbase.com/avatar/r/art_lover3167.jpg",
      "video": null,
      "image": "https://images.animefansbase.com/artwork/md/2023/09/27345-65055d6572ee5.jpeg",
      "postDate": "2023-09-16 07:46:46",
      "likes": 0,
      "comment": 0,
      "totalRepost": 0,
      "isLiked": false,
      "isRepost": 0,
      "commentPreview": null
    },
    {
      "categoryId": 8449,
      "id": 25903,
      "username": "@ralex_",
      "fullName": "Robin Alexander",
      "avatar": "https://images.animefansbase.com/avatar/r/ralex_65380.jpg",
      "video": null,
      "image": "https://images.animefansbase.com/artwork/md/2023/09/95673-65046cc683364.jpg",
      "postDate": "2023-09-15 14:40:06",
      "likes": 1,
      "comment": 0,
      "totalRepost": 0,
      "isLiked": false,
      "isRepost": 0,
      "commentPreview": null
    },
    {
      "categoryId": 8448,
      "id": 25901,
      "username": "@art_lover",
      "fullName": "Jasmine ❤️",
      "avatar": "https://images.animefansbase.com/avatar/r/art_lover3167.jpg",
      "video": null,
      "image": "https://images.animefansbase.com/artwork/md/2023/09/25624-6504100450fb8.jpeg",
      "postDate": "2023-09-15 08:04:20",
      "likes": 0,
      "comment": 0,
      "totalRepost": 0,
      "isLiked": false,
      "isRepost": 0,
      "commentPreview": null
    },
    {
      "categoryId": 8447,
      "id": 25900,
      "username": "@ralex_",
      "fullName": "Robin Alexander",
      "avatar": "https://images.animefansbase.com/avatar/r/ralex_65380.jpg",
      "video": null,
      "image": "https://images.animefansbase.com/artwork/md/2023/09/63873-6503f12de0064.jpeg",
      "postDate": "2023-09-15 05:52:46",
      "likes": 1,
      "comment": 0,
      "totalRepost": 0,
      "isLiked": false,
      "isRepost": 0,
      "commentPreview": null
    },
    {
      "categoryId": 8446,
      "id": 25899,
      "username": "@darkdragonet100",
      "fullName": "disastercat10",
      "avatar": "https://images.animefansbase.com/avatar/r/darkdragonet10065615.jpg",
      "video": null,
      "image": "https://images.animefansbase.com/artwork/md/2023/09/4328-6503c37fe4d3f.jpeg",
      "postDate": "2023-09-15 02:37:52",
      "likes": 5,
      "comment": 0,
      "totalRepost": 0,
      "isLiked": false,
      "isRepost": 0,
      "commentPreview": null
    },
    {
      "categoryId": 8445,
      "id": 25895,
      "username": "@art_lover",
      "fullName": "Jasmine ❤️",
      "avatar": "https://images.animefansbase.com/avatar/r/art_lover3167.jpg",
      "video": null,
      "image": "https://images.animefansbase.com/artwork/md/2023/09/83353-65032ae2f0c0a.jpeg",
      "postDate": "2023-09-14 15:46:43",
      "likes": 2,
      "comment": 0,
      "totalRepost": 0,
      "isLiked": false,
      "isRepost": 0,
      "commentPreview": null
    },
    {
      "categoryId": 8428,
      "id": 25851,
      "username": "@art_lover",
      "fullName": "Jasmine ❤️",
      "avatar": "https://images.animefansbase.com/avatar/r/art_lover3167.jpg",
      "video": null,
      "image": "https://images.animefansbase.com/artwork/md/2023/09/36796-64fdc24bb48e2.jpeg",
      "postDate": "2023-09-10 13:19:07",
      "likes": 1,
      "comment": 0,
      "totalRepost": 0,
      "isLiked": false,
      "isRepost": 0,
      "commentPreview": null
    },
    {
      "categoryId": 8427,
      "id": 25848,
      "username": "@ralex_",
      "fullName": "Robin Alexander",
      "avatar": "https://images.animefansbase.com/avatar/r/ralex_65380.jpg",
      "video": null,
      "image": "https://images.animefansbase.com/artwork/md/2023/09/79251-64fd91ebf3f08.jpeg",
      "postDate": "2023-09-10 09:52:44",
      "likes": 3,
      "comment": 0,
      "totalRepost": 0,
      "isLiked": false,
      "isRepost": 0,
      "commentPreview": null
    },
    {
      "categoryId": 8426,
      "id": 25845,
      "username": "@art_lover",
      "fullName": "Jasmine ❤️",
      "avatar": "https://images.animefansbase.com/avatar/r/art_lover3167.jpg",
      "video": null,
      "image": "https://images.animefansbase.com/artwork/md/2023/09/58488-64fd5c4a5f0e6.jpeg",
      "postDate": "2023-09-10 06:03:54",
      "likes": 5,
      "comment": 0,
      "totalRepost": 0,
      "isLiked": false,
      "isRepost": 0,
      "commentPreview": null
    },
    {
      "categoryId": 8425,
      "id": 25841,
      "username": "@ralex_",
      "fullName": "Robin Alexander",
      "avatar": "https://images.animefansbase.com/avatar/r/ralex_65380.jpg",
      "video": null,
      "image": "https://images.animefansbase.com/artwork/md/2023/09/47679-64fca8424008a.jpeg",
      "postDate": "2023-09-09 17:15:46",
      "likes": 2,
      "comment": 0,
      "totalRepost": 0,
      "isLiked": false,
      "isRepost": 0,
      "commentPreview": null
    },
    {
      "categoryId": 8424,
      "id": 25839,
      "username": "@art_lover",
      "fullName": "Jasmine ❤️",
      "avatar": "https://images.animefansbase.com/avatar/r/art_lover3167.jpg",
      "video": null,
      "image": "https://images.animefansbase.com/artwork/md/2023/09/95963-64fc8502b4b1f.jpeg",
      "postDate": "2023-09-09 14:45:23",
      "likes": 2,
      "comment": 0,
      "totalRepost": 0,
      "isLiked": false,
      "isRepost": 0,
      "commentPreview": null
    },
    {
      "categoryId": 8423,
      "id": 25835,
      "username": "@ralex_",
      "fullName": "Robin Alexander",
      "avatar": "https://images.animefansbase.com/avatar/r/ralex_65380.jpg",
      "video": null,
      "image": "https://images.animefansbase.com/artwork/md/2023/09/35332-64fc45361a56b.jpeg",
      "postDate": "2023-09-09 10:13:10",
      "likes": 2,
      "comment": 0,
      "totalRepost": 0,
      "isLiked": false,
      "isRepost": 0,
      "commentPreview": null
    },
    {
      "categoryId": 8422,
      "id": 25834,
      "username": "@alphawolf",
      "fullName": "Hussain Alpha",
      "avatar": "https://images.animefansbase.com/avatar/r/alphawolf30585.jpg",
      "video": null,
      "image": "https://images.animefansbase.com/artwork/md/2023/09/96509-64fc29d4c27fb.jpeg",
      "postDate": "2023-09-09 08:16:20",
      "likes": 3,
      "comment": 0,
      "totalRepost": 0,
      "isLiked": false,
      "isRepost": 0,
      "commentPreview": null
    },
    {
      "categoryId": 8421,
      "id": 25830,
      "username": "@art_lover",
      "fullName": "Jasmine ❤️",
      "avatar": "https://images.animefansbase.com/avatar/r/art_lover3167.jpg",
      "video": null,
      "image": "https://images.animefansbase.com/artwork/md/2023/09/29473-64fc01cb63d84.jpg",
      "postDate": "2023-09-09 05:25:31",
      "likes": 1,
      "comment": 0,
      "totalRepost": 0,
      "isLiked": false,
      "isRepost": 0,
      "commentPreview": null
    },
    {
      "categoryId": 8418,
      "id": 25821,
      "username": "@art_lover",
      "fullName": "Jasmine ❤️",
      "avatar": "https://images.animefansbase.com/avatar/r/art_lover3167.jpg",
      "video": null,
      "image": "https://images.animefansbase.com/artwork/md/2023/09/36533-64fb6e140616f.jpeg",
      "postDate": "2023-09-08 18:55:16",
      "likes": 0,
      "comment": 0,
      "totalRepost": 0,
      "isLiked": false,
      "isRepost": 0,
      "commentPreview": null
    },
    {
      "categoryId": 8416,
      "id": 25813,
      "username": "@art_lover",
      "fullName": "Jasmine ❤️",
      "avatar": "https://images.animefansbase.com/avatar/r/art_lover3167.jpg",
      "video": null,
      "image": "https://images.animefansbase.com/artwork/md/2023/09/19070-64fa985f2544d.jpeg",
      "postDate": "2023-09-08 03:43:27",
      "likes": 1,
      "comment": 0,
      "totalRepost": 0,
      "isLiked": false,
      "isRepost": 0,
      "commentPreview": null
    },
    {
      "categoryId": 8415,
      "id": 25802,
      "username": "@art_lover",
      "fullName": "Jasmine ❤️",
      "avatar": "https://images.animefansbase.com/avatar/r/art_lover3167.jpg",
      "video": null,
      "image": "https://images.animefansbase.com/artwork/md/2023/09/1215-64f995b33e6b1.jpeg",
      "postDate": "2023-09-07 09:19:47",
      "likes": 1,
      "comment": 0,
      "totalRepost": 0,
      "isLiked": false,
      "isRepost": 0,
      "commentPreview": null
    },
    {
      "categoryId": 8414,
      "id": 25800,
      "username": "@ralex_",
      "fullName": "Robin Alexander",
      "avatar": "https://images.animefansbase.com/avatar/r/ralex_65380.jpg",
      "video": null,
      "image": "https://images.animefansbase.com/artwork/md/2023/09/89732-64f9435b3108a.jpeg",
      "postDate": "2023-09-07 03:28:27",
      "likes": 0,
      "comment": 0,
      "totalRepost": 0,
      "isLiked": false,
      "isRepost": 0,
      "commentPreview": null
    },
    {
      "categoryId": 8413,
      "id": 25799,
      "username": "@art_lover",
      "fullName": "Jasmine ❤️",
      "avatar": "https://images.animefansbase.com/avatar/r/art_lover3167.jpg",
      "video": null,
      "image": "https://images.animefansbase.com/artwork/md/2023/09/99921-64f8bd9a9504a.jpeg",
      "postDate": "2023-09-06 17:57:46",
      "likes": 0,
      "comment": 0,
      "totalRepost": 0,
      "isLiked": false,
      "isRepost": 0,
      "commentPreview": null
    },
    {
      "categoryId": 8412,
      "id": 25792,
      "username": "@ralex_",
      "fullName": "Robin Alexander",
      "avatar": "https://images.animefansbase.com/avatar/r/ralex_65380.jpg",
      "video": null,
      "image": "https://images.animefansbase.com/artwork/md/2023/09/46391-64f84da13e2ed.jpeg",
      "postDate": "2023-09-06 10:00:01",
      "likes": 2,
      "comment": 0,
      "totalRepost": 0,
      "isLiked": false,
      "isRepost": 0,
      "commentPreview": null
    },
    {
      "categoryId": 8411,
      "id": 25788,
      "username": "@art_lover",
      "fullName": "Jasmine ❤️",
      "avatar": "https://images.animefansbase.com/avatar/r/art_lover3167.jpg",
      "video": null,
      "image": "https://images.animefansbase.com/artwork/md/2023/09/71448-64f81ae7cd1a4.jpeg",
      "postDate": "2023-09-06 06:23:36",
      "likes": 1,
      "comment": 1,
      "totalRepost": 0,
      "isLiked": false,
      "isRepost": 0,
      "commentPreview": {
        "id": "707",
        "image": null,
        "avatar": "soomii30429.jpg",
        "fullName": "Soomi Is Here",
        "username": "@soomii",
        "postDate": "2023-09-06 12:20:09",
        "commentTxt": "Is she from one piece princess vevy"
      }
    },
    {
      "categoryId": 8410,
      "id": 25787,
      "username": "@animelover",
      "fullName": "Animelover",
      "avatar": "https://images.animefansbase.com/avatar/r/animelover7816.jpg",
      "video": null,
      "image": "https://images.animefansbase.com/artwork/md/2023/09/63670-64f7ee476e785.jpeg",
      "postDate": "2023-09-06 03:13:11",
      "likes": 1,
      "comment": 0,
      "totalRepost": 0,
      "isLiked": false,
      "isRepost": 0,
      "commentPreview": null
    },
    {
      "categoryId": 8409,
      "id": 25781,
      "username": "@ralex_",
      "fullName": "Robin Alexander",
      "avatar": "https://images.animefansbase.com/avatar/r/ralex_65380.jpg",
      "video": null,
      "image": "https://images.animefansbase.com/artwork/md/2023/09/26739-64f73d25cc195.jpg",
      "postDate": "2023-09-05 14:37:26",
      "likes": 3,
      "comment": 0,
      "totalRepost": 0,
      "isLiked": false,
      "isRepost": 0,
      "commentPreview": null
    },
    {
      "categoryId": 8408,
      "id": 25777,
      "username": "@art_lover",
      "fullName": "Jasmine ❤️",
      "avatar": "https://images.animefansbase.com/avatar/r/art_lover3167.jpg",
      "video": null,
      "image": "https://images.animefansbase.com/artwork/md/2023/09/67643-64f6fa9f9e1d4.jpeg",
      "postDate": "2023-09-05 09:53:35",
      "likes": 1,
      "comment": 0,
      "totalRepost": 0,
      "isLiked": false,
      "isRepost": 0,
      "commentPreview": null
    },
    {
      "categoryId": 8407,
      "id": 25770,
      "username": "@ralex_",
      "fullName": "Robin Alexander",
      "avatar": "https://images.animefansbase.com/avatar/r/ralex_65380.jpg",
      "video": null,
      "image": "https://images.animefansbase.com/artwork/md/2023/09/14567-64f6bff21b4e2.jpeg",
      "postDate": "2023-09-05 05:43:14",
      "likes": 3,
      "comment": 0,
      "totalRepost": 0,
      "isLiked": false,
      "isRepost": 0,
      "commentPreview": null
    },
    {
      "categoryId": 8406,
      "id": 25765,
      "username": "@art_lover",
      "fullName": "Jasmine ❤️",
      "avatar": "https://images.animefansbase.com/avatar/r/art_lover3167.jpg",
      "video": null,
      "image": "https://images.animefansbase.com/artwork/md/2023/09/21575-64f60117d2fe4.jpeg",
      "postDate": "2023-09-04 16:08:56",
      "likes": 2,
      "comment": 0,
      "totalRepost": 0,
      "isLiked": false,
      "isRepost": 0,
      "commentPreview": null
    },
    {
      "categoryId": 8405,
      "id": 25762,
      "username": "@ralex_",
      "fullName": "Robin Alexander",
      "avatar": "https://images.animefansbase.com/avatar/r/ralex_65380.jpg",
      "video": null,
      "image": "https://images.animefansbase.com/artwork/md/2023/09/21311-64f59851a46cf.jpeg",
      "postDate": "2023-09-04 08:41:55",
      "likes": 0,
      "comment": 0,
      "totalRepost": 0,
      "isLiked": false,
      "isRepost": 0,
      "commentPreview": null
    },
    {
      "categoryId": 8404,
      "id": 25760,
      "username": "@art_lover",
      "fullName": "Jasmine ❤️",
      "avatar": "https://images.animefansbase.com/avatar/r/art_lover3167.jpg",
      "video": null,
      "image": "https://images.animefansbase.com/artwork/md/2023/09/30252-64f56f7e98da0.jpg",
      "postDate": "2023-09-04 05:47:42",
      "likes": 1,
      "comment": 0,
      "totalRepost": 0,
      "isLiked": false,
      "isRepost": 0,
      "commentPreview": null
    },
    {
      "categoryId": 8403,
      "id": 25756,
      "username": "@ralex_",
      "fullName": "Robin Alexander",
      "avatar": "https://images.animefansbase.com/avatar/r/ralex_65380.jpg",
      "video": null,
      "image": "https://images.animefansbase.com/artwork/md/2023/09/68232-64f4cd3896a0d.jpeg",
      "postDate": "2023-09-03 18:15:20",
      "likes": 1,
      "comment": 0,
      "totalRepost": 0,
      "isLiked": false,
      "isRepost": 0,
      "commentPreview": null
    },
    {
      "categoryId": 8402,
      "id": 25751,
      "username": "@art_lover",
      "fullName": "Jasmine ❤️",
      "avatar": "https://images.animefansbase.com/avatar/r/art_lover3167.jpg",
      "video": null,
      "image": "https://images.animefansbase.com/artwork/md/2023/09/6711-64f4ba4d9723e.jpeg",
      "postDate": "2023-09-03 16:54:37",
      "likes": 2,
      "comment": 0,
      "totalRepost": 0,
      "isLiked": false,
      "isRepost": 0,
      "commentPreview": null
    },
    {
      "categoryId": 8401,
      "id": 25739,
      "username": "@art_lover",
      "fullName": "Jasmine ❤️",
      "avatar": "https://images.animefansbase.com/avatar/r/art_lover3167.jpg",
      "video": null,
      "image": "https://images.animefansbase.com/artwork/md/2023/09/79367-64f42db2de538.jpg",
      "postDate": "2023-09-03 06:54:43",
      "likes": 3,
      "comment": 0,
      "totalRepost": 0,
      "isLiked": false,
      "isRepost": 0,
      "commentPreview": null
    },
    {
      "categoryId": 8400,
      "id": 25737,
      "username": "@ralex_",
      "fullName": "Robin Alexander",
      "avatar": "https://images.animefansbase.com/avatar/r/ralex_65380.jpg",
      "video": null,
      "image": "https://images.animefansbase.com/artwork/md/2023/09/94987-64f3f1184617d.jpeg",
      "postDate": "2023-09-03 02:36:08",
      "likes": 2,
      "comment": 0,
      "totalRepost": 0,
      "isLiked": false,
      "isRepost": 0,
      "commentPreview": null
    },
    {
      "categoryId": 8399,
      "id": 25726,
      "username": "@ralex_",
      "fullName": "Robin Alexander",
      "avatar": "https://images.animefansbase.com/avatar/r/ralex_65380.jpg",
      "video": null,
      "image": "https://images.animefansbase.com/artwork/md/2023/09/47316-64f2ffae7b68b.jpeg",
      "postDate": "2023-09-02 09:26:06",
      "likes": 3,
      "comment": 1,
      "totalRepost": 0,
      "isLiked": false,
      "isRepost": 0,
      "commentPreview": {
        "id": "640",
        "image": null,
        "avatar": "soomin98786.jpg",
        "fullName": "Soomin Is Here",
        "username": "@soomin",
        "postDate": "2023-09-02 09:26:59",
        "commentTxt": "Hello"
      }
    },
    {
      "categoryId": 8397,
      "id": 25715,
      "username": "@art_lover",
      "fullName": "Jasmine ❤️",
      "avatar": "https://images.animefansbase.com/avatar/r/art_lover3167.jpg",
      "video": null,
      "image": "https://images.animefansbase.com/artwork/md/2023/09/78669-64f2dede417ae.jpeg",
      "postDate": "2023-09-02 07:06:06",
      "likes": 4,
      "comment": 1,
      "totalRepost": 0,
      "isLiked": false,
      "isRepost": 0,
      "commentPreview": {
        "id": "627",
        "image": null,
        "avatar": "gojo721.jpg",
        "fullName": "Itachi Uchiha",
        "username": "@gojo",
        "postDate": "2023-09-02 07:52:35",
        "commentTxt": "Hello"
      }
    },
    {
      "categoryId": 8396,
      "id": 25712,
      "username": "@ralex_",
      "fullName": "Robin Alexander",
      "avatar": "https://images.animefansbase.com/avatar/r/ralex_65380.jpg",
      "video": null,
      "image": "https://images.animefansbase.com/artwork/md/2023/09/10423-64f2a1f4c4f0c.jpg",
      "postDate": "2023-09-02 02:46:13",
      "likes": 1,
      "comment": 1,
      "totalRepost": 0,
      "isLiked": false,
      "isRepost": 0,
      "commentPreview": {
        "id": "634",
        "image": null,
        "avatar": "gojo721.jpg",
        "fullName": "Itachi Uchiha",
        "username": "@gojo",
        "postDate": "2023-09-02 08:24:04",
        "commentTxt": "Relex"
      }
    },
    {
      "categoryId": 8395,
      "id": 25699,
      "username": "@art_lover",
      "fullName": "Jasmine ❤️",
      "avatar": "https://images.animefansbase.com/avatar/r/art_lover3167.jpg",
      "video": null,
      "image": "https://images.animefansbase.com/artwork/md/2023/09/86703-64f1dabee0de2.jpeg",
      "postDate": "2023-09-01 12:36:15",
      "likes": 1,
      "comment": 1,
      "totalRepost": 0,
      "isLiked": false,
      "isRepost": 0,
      "commentPreview": {
        "id": "604",
        "image": null,
        "avatar": "gojo721.jpg",
        "fullName": "Itachi Uchiha",
        "username": "@gojo",
        "postDate": "2023-09-01 19:30:30",
        "commentTxt": "Hi kiddo"
      }
    },
    {
      "categoryId": 8394,
      "id": 25694,
      "username": "@art_lover",
      "fullName": "Jasmine ❤️",
      "avatar": "https://images.animefansbase.com/avatar/r/art_lover3167.jpg",
      "video": null,
      "image": "https://images.animefansbase.com/artwork/md/2023/09/597-64f19905e8292.jpeg",
      "postDate": "2023-09-01 07:55:50",
      "likes": 2,
      "comment": 0,
      "totalRepost": 0,
      "isLiked": false,
      "isRepost": 0,
      "commentPreview": null
    },
    {
      "categoryId": 8393,
      "id": 25688,
      "username": "@art_lover",
      "fullName": "Jasmine ❤️",
      "avatar": "https://images.animefansbase.com/avatar/r/art_lover3167.jpg",
      "video": null,
      "image": "https://images.animefansbase.com/artwork/md/2023/08/42125-64f0b9ea74180.jpeg",
      "postDate": "2023-08-31 16:03:54",
      "likes": 2,
      "comment": 0,
      "totalRepost": 0,
      "isLiked": false,
      "isRepost": 0,
      "commentPreview": null
    },
    {
      "categoryId": 8392,
      "id": 25686,
      "username": "@ralex_",
      "fullName": "Robin Alexander",
      "avatar": "https://images.animefansbase.com/avatar/r/ralex_65380.jpg",
      "video": null,
      "image": "https://images.animefansbase.com/artwork/md/2023/08/42475-64f076d58197f.jpeg",
      "postDate": "2023-08-31 11:17:41",
      "likes": 3,
      "comment": 0,
      "totalRepost": 0,
      "isLiked": false,
      "isRepost": 0,
      "commentPreview": null
    },
    {
      "categoryId": 8391,
      "id": 25682,
      "username": "@art_lover",
      "fullName": "Jasmine ❤️",
      "avatar": "https://images.animefansbase.com/avatar/r/art_lover3167.jpg",
      "video": null,
      "image": "https://images.animefansbase.com/artwork/md/2023/08/75632-64f032a2ef608.jpeg",
      "postDate": "2023-08-31 06:26:43",
      "likes": 3,
      "comment": 4,
      "totalRepost": 0,
      "isLiked": false,
      "isRepost": 0,
      "commentPreview": {
        "id": "575",
        "image": null,
        "avatar": "gojo721.jpg",
        "fullName": "Itachi Uchiha",
        "username": "@gojo",
        "postDate": "2023-08-31 07:22:50",
        "commentTxt": "Gojo from ohayo"
      }
    },
    {
      "categoryId": 8390,
      "id": 25680,
      "username": "@ralex_",
      "fullName": "Robin Alexander",
      "avatar": "https://images.animefansbase.com/avatar/r/ralex_65380.jpg",
      "video": null,
      "image": "https://images.animefansbase.com/artwork/md/2023/08/40497-64f0062fdb0e0.jpeg",
      "postDate": "2023-08-31 03:17:04",
      "likes": 2,
      "comment": 2,
      "totalRepost": 0,
      "isLiked": false,
      "isRepost": 0,
      "commentPreview": {
        "id": "581",
        "image": null,
        "avatar": "gojo721.jpg",
        "fullName": "Itachi Uchiha",
        "username": "@gojo",
        "postDate": "2023-08-31 07:43:12",
        "commentTxt": "She looks like Nokia"
      }
    },
    {
      "categoryId": 8389,
      "id": 25672,
      "username": "@ralex_",
      "fullName": "Robin Alexander",
      "avatar": "https://images.animefansbase.com/avatar/r/ralex_65380.jpg",
      "video": null,
      "image": "https://images.animefansbase.com/artwork/md/2023/08/34496-64ef171c80791.jpeg",
      "postDate": "2023-08-30 10:17:00",
      "likes": 3,
      "comment": 0,
      "totalRepost": 0,
      "isLiked": false,
      "isRepost": 0,
      "commentPreview": null
    },
    {
      "categoryId": 8388,
      "id": 25665,
      "username": "@art_lover",
      "fullName": "Jasmine ❤️",
      "avatar": "https://images.animefansbase.com/avatar/r/art_lover3167.jpg",
      "video": null,
      "image": "https://images.animefansbase.com/artwork/md/2023/08/70439-64eede162abab.jpeg",
      "postDate": "2023-08-30 06:13:42",
      "likes": 2,
      "comment": 1,
      "totalRepost": 0,
      "isLiked": false,
      "isRepost": 0,
      "commentPreview": {
        "id": "557",
        "image": null,
        "avatar": "gojo721.jpg",
        "fullName": "Itachi Uchiha",
        "username": "@gojo",
        "postDate": "2023-08-30 07:47:40",
        "commentTxt": "Lol"
      }
    },
    {
      "categoryId": 8387,
      "id": 25653,
      "username": "@art_lover",
      "fullName": "Jasmine ❤️",
      "avatar": "https://images.animefansbase.com/avatar/r/art_lover3167.jpg",
      "video": null,
      "image": "https://images.animefansbase.com/artwork/md/2023/08/95156-64ee133610947.jpeg",
      "postDate": "2023-08-29 15:48:06",
      "likes": 3,
      "comment": 0,
      "totalRepost": 0,
      "isLiked": false,
      "isRepost": 0,
      "commentPreview": null
    },
    {
      "categoryId": 8386,
      "id": 25650,
      "username": "@ralex_",
      "fullName": "Robin Alexander",
      "avatar": "https://images.animefansbase.com/avatar/r/ralex_65380.jpg",
      "video": null,
      "image": "https://images.animefansbase.com/artwork/md/2023/08/3719-64edd7fbba1c5.jpeg",
      "postDate": "2023-08-29 11:35:24",
      "likes": 2,
      "comment": 0,
      "totalRepost": 0,
      "isLiked": false,
      "isRepost": 0,
      "commentPreview": null
    },
    {
      "categoryId": 8385,
      "id": 25648,
      "username": "@art_lover",
      "fullName": "Jasmine ❤️",
      "avatar": "https://images.animefansbase.com/avatar/r/art_lover3167.jpg",
      "video": null,
      "image": "https://images.animefansbase.com/artwork/md/2023/08/94365-64eda65474195.jpeg",
      "postDate": "2023-08-29 08:03:32",
      "likes": 2,
      "comment": 0,
      "totalRepost": 0,
      "isLiked": false,
      "isRepost": 0,
      "commentPreview": null
    },
    {
      "categoryId": 8384,
      "id": 25641,
      "username": "@ralex_",
      "fullName": "Robin Alexander",
      "avatar": "https://images.animefansbase.com/avatar/r/ralex_65380.jpg",
      "video": null,
      "image": "https://images.animefansbase.com/artwork/md/2023/08/60361-64ed6625bfc2d.jpeg",
      "postDate": "2023-08-29 03:29:42",
      "likes": 1,
      "comment": 0,
      "totalRepost": 0,
      "isLiked": false,
      "isRepost": 0,
      "commentPreview": null
    },
    {
      "categoryId": 8383,
      "id": 25635,
      "username": "@art_lover",
      "fullName": "Jasmine ❤️",
      "avatar": "https://images.animefansbase.com/avatar/r/art_lover3167.jpg",
      "video": null,
      "image": "https://images.animefansbase.com/artwork/md/2023/08/53519-64ecc13177e16.jpeg",
      "postDate": "2023-08-28 15:45:53",
      "likes": 1,
      "comment": 0,
      "totalRepost": 0,
      "isLiked": false,
      "isRepost": 0,
      "commentPreview": null
    },
    {
      "categoryId": 8382,
      "id": 25633,
      "username": "@ralex_",
      "fullName": "Robin Alexander",
      "avatar": "https://images.animefansbase.com/avatar/r/ralex_65380.jpg",
      "video": null,
      "image": "https://images.animefansbase.com/artwork/md/2023/08/14095-64ec75bbac69e.jpeg",
      "postDate": "2023-08-28 10:23:56",
      "likes": 1,
      "comment": 0,
      "totalRepost": 0,
      "isLiked": false,
      "isRepost": 0,
      "commentPreview": null
    },
    {
      "categoryId": 8381,
      "id": 25631,
      "username": "@art_lover",
      "fullName": "Jasmine ❤️",
      "avatar": "https://images.animefansbase.com/avatar/r/art_lover3167.jpg",
      "video": null,
      "image": "https://images.animefansbase.com/artwork/md/2023/08/2574-64ec3e477ab1e.jpeg",
      "postDate": "2023-08-28 06:27:19",
      "likes": 1,
      "comment": 0,
      "totalRepost": 0,
      "isLiked": false,
      "isRepost": 0,
      "commentPreview": null
    },
    {
      "categoryId": 8380,
      "id": 25628,
      "username": "@ralex_",
      "fullName": "Robin Alexander",
      "avatar": "https://images.animefansbase.com/avatar/r/ralex_65380.jpg",
      "video": null,
      "image": "https://images.animefansbase.com/artwork/md/2023/08/39997-64eb87d306002.jpeg",
      "postDate": "2023-08-27 17:28:51",
      "likes": 2,
      "comment": 0,
      "totalRepost": 0,
      "isLiked": false,
      "isRepost": 0,
      "commentPreview": null
    },
    {
      "categoryId": 8363,
      "id": 25572,
      "username": "@art_lover",
      "fullName": "Jasmine ❤️",
      "avatar": "https://images.animefansbase.com/avatar/r/art_lover3167.jpg",
      "video": null,
      "image": "https://images.animefansbase.com/artwork/md/2023/08/47358-64e4483d1399b.jpeg",
      "postDate": "2023-08-22 05:31:42",
      "likes": 1,
      "comment": 0,
      "totalRepost": 0,
      "isLiked": false,
      "isRepost": 0,
      "commentPreview": null
    },
    {
      "categoryId": 8362,
      "id": 25569,
      "username": "@ralex_",
      "fullName": "Robin Alexander",
      "avatar": "https://images.animefansbase.com/avatar/r/ralex_65380.jpg",
      "video": null,
      "image": "https://images.animefansbase.com/artwork/md/2023/08/71004-64e3b3e973302.jpeg",
      "postDate": "2023-08-21 18:58:50",
      "likes": 1,
      "comment": 0,
      "totalRepost": 0,
      "isLiked": false,
      "isRepost": 0,
      "commentPreview": null
    },
    {
      "categoryId": 8361,
      "id": 25565,
      "username": "@art_lover",
      "fullName": "Jasmine ❤️",
      "avatar": "https://images.animefansbase.com/avatar/r/art_lover3167.jpg",
      "video": null,
      "image": "https://images.animefansbase.com/artwork/md/2023/08/55964-64e374e45f031.jpeg",
      "postDate": "2023-08-21 14:29:57",
      "likes": 1,
      "comment": 0,
      "totalRepost": 0,
      "isLiked": false,
      "isRepost": 0,
      "commentPreview": null
    },
    {
      "categoryId": 8360,
      "id": 25558,
      "username": "@ralex_",
      "fullName": "Robin Alexander",
      "avatar": "https://images.animefansbase.com/avatar/r/ralex_65380.jpg",
      "video": null,
      "image": "https://images.animefansbase.com/artwork/md/2023/08/8022-64e32a135a02d.jpeg",
      "postDate": "2023-08-21 09:10:43",
      "likes": 2,
      "comment": 0,
      "totalRepost": 0,
      "isLiked": false,
      "isRepost": 0,
      "commentPreview": null
    },
    {
      "categoryId": 8359,
      "id": 25555,
      "username": "@art_lover",
      "fullName": "Jasmine ❤️",
      "avatar": "https://images.animefansbase.com/avatar/r/art_lover3167.jpg",
      "video": null,
      "image": "https://images.animefansbase.com/artwork/md/2023/08/44520-64e2f3a2dcdf8.jpeg",
      "postDate": "2023-08-21 05:18:28",
      "likes": 2,
      "comment": 0,
      "totalRepost": 0,
      "isLiked": false,
      "isRepost": 0,
      "commentPreview": null
    },
    {
      "categoryId": 8357,
      "id": 25547,
      "username": "@art_lover",
      "fullName": "Jasmine ❤️",
      "avatar": "https://images.animefansbase.com/avatar/r/art_lover3167.jpg",
      "video": null,
      "image": "https://images.animefansbase.com/artwork/md/2023/08/33041-64e24011a5364.jpeg",
      "postDate": "2023-08-20 16:32:18",
      "likes": 0,
      "comment": 0,
      "totalRepost": 0,
      "isLiked": false,
      "isRepost": 0,
      "commentPreview": null
    },
    {
      "categoryId": 8356,
      "id": 25545,
      "username": "@ralex_",
      "fullName": "Robin Alexander",
      "avatar": "https://images.animefansbase.com/avatar/r/ralex_65380.jpg",
      "video": null,
      "image": "https://images.animefansbase.com/artwork/md/2023/08/86285-64e204b202827.jpeg",
      "postDate": "2023-08-20 12:18:58",
      "likes": 1,
      "comment": 0,
      "totalRepost": 0,
      "isLiked": false,
      "isRepost": 0,
      "commentPreview": null
    },
    {
      "categoryId": 8355,
      "id": 25542,
      "username": "@art_lover",
      "fullName": "Jasmine ❤️",
      "avatar": "https://images.animefansbase.com/avatar/r/art_lover3167.jpg",
      "video": null,
      "image": "https://images.animefansbase.com/artwork/md/2023/08/51532-64e18e8c174d0.jpeg",
      "postDate": "2023-08-20 03:54:53",
      "likes": 0,
      "comment": 0,
      "totalRepost": 0,
      "isLiked": false,
      "isRepost": 0,
      "commentPreview": null
    },
    {
      "categoryId": 8354,
      "id": 25536,
      "username": "@art_lover",
      "fullName": "Jasmine ❤️",
      "avatar": "https://images.animefansbase.com/avatar/r/art_lover3167.jpg",
      "video": null,
      "image": "https://images.animefansbase.com/artwork/md/2023/08/12883-64e0fb1c68537.jpg",
      "postDate": "2023-08-19 17:25:48",
      "likes": 1,
      "comment": 0,
      "totalRepost": 0,
      "isLiked": false,
      "isRepost": 0,
      "commentPreview": null
    },
    {
      "categoryId": 8353,
      "id": 25534,
      "username": "@ralex_",
      "fullName": "Robin Alexander",
      "avatar": "https://images.animefansbase.com/avatar/r/ralex_65380.jpg",
      "video": null,
      "image": "https://images.animefansbase.com/artwork/md/2023/08/10300-64e0a46415502.jpeg",
      "postDate": "2023-08-19 11:15:49",
      "likes": 1,
      "comment": 0,
      "totalRepost": 0,
      "isLiked": false,
      "isRepost": 0,
      "commentPreview": null
    },
    {
      "categoryId": 8352,
      "id": 25533,
      "username": "@art_lover",
      "fullName": "Jasmine ❤️",
      "avatar": "https://images.animefansbase.com/avatar/r/art_lover3167.jpg",
      "video": null,
      "image": "https://images.animefansbase.com/artwork/md/2023/08/61392-64e076c1af7a2.jpeg",
      "postDate": "2023-08-19 08:01:07",
      "likes": 1,
      "comment": 0,
      "totalRepost": 0,
      "isLiked": false,
      "isRepost": 0,
      "commentPreview": null
    },
    {
      "categoryId": 8351,
      "id": 25525,
      "username": "@ralex_",
      "fullName": "Robin Alexander",
      "avatar": "https://images.animefansbase.com/avatar/r/ralex_65380.jpg",
      "video": null,
      "image": "https://images.animefansbase.com/artwork/md/2023/08/11708-64dfc025a46d8.jpeg",
      "postDate": "2023-08-18 19:01:58",
      "likes": 2,
      "comment": 0,
      "totalRepost": 0,
      "isLiked": false,
      "isRepost": 0,
      "commentPreview": null
    },
    {
      "categoryId": 8350,
      "id": 25524,
      "username": "@art_lover",
      "fullName": "Jasmine ❤️",
      "avatar": "https://images.animefansbase.com/avatar/r/art_lover3167.jpg",
      "video": null,
      "image": "https://images.animefansbase.com/artwork/md/2023/08/27534-64dfa1782eb49.jpeg",
      "postDate": "2023-08-18 16:51:05",
      "likes": 2,
      "comment": 0,
      "totalRepost": 0,
      "isLiked": false,
      "isRepost": 0,
      "commentPreview": null
    },
    {
      "categoryId": 8349,
      "id": 25517,
      "username": "@ralex_",
      "fullName": "Robin Alexander",
      "avatar": "https://images.animefansbase.com/avatar/r/ralex_65380.jpg",
      "video": null,
      "image": "https://images.animefansbase.com/artwork/md/2023/08/6451-64df41fec93fd.jpeg",
      "postDate": "2023-08-18 10:03:44",
      "likes": 0,
      "comment": 0,
      "totalRepost": 0,
      "isLiked": false,
      "isRepost": 0,
      "commentPreview": null
    },
    {
      "categoryId": 8348,
      "id": 25515,
      "username": "@art_lover",
      "fullName": "Jasmine ❤️",
      "avatar": "https://images.animefansbase.com/avatar/r/art_lover3167.jpg",
      "video": null,
      "image": "https://images.animefansbase.com/artwork/md/2023/08/13119-64df19dc682e0.jpeg",
      "postDate": "2023-08-18 07:12:29",
      "likes": 0,
      "comment": 0,
      "totalRepost": 0,
      "isLiked": false,
      "isRepost": 0,
      "commentPreview": null
    },
    {
      "categoryId": 8347,
      "id": 25511,
      "username": "@ralex_",
      "fullName": "Robin Alexander",
      "avatar": "https://images.animefansbase.com/avatar/r/ralex_65380.jpg",
      "video": null,
      "image": "https://images.animefansbase.com/artwork/md/2023/08/53812-64decc65e5efa.jpeg",
      "postDate": "2023-08-18 01:41:59",
      "likes": 0,
      "comment": 0,
      "totalRepost": 0,
      "isLiked": false,
      "isRepost": 0,
      "commentPreview": null
    },
    {
      "categoryId": 8346,
      "id": 25501,
      "username": "@art_lover",
      "fullName": "Jasmine ❤️",
      "avatar": "https://images.animefansbase.com/avatar/r/art_lover3167.jpg",
      "video": null,
      "image": "https://images.animefansbase.com/artwork/md/2023/08/26120-64de28bc2078a.jpeg",
      "postDate": "2023-08-17 14:03:41",
      "likes": 0,
      "comment": 0,
      "totalRepost": 0,
      "isLiked": false,
      "isRepost": 0,
      "commentPreview": null
    },
    {
      "categoryId": 8344,
      "id": 25496,
      "username": "@art_lover",
      "fullName": "Jasmine ❤️",
      "avatar": "https://images.animefansbase.com/avatar/r/art_lover3167.jpg",
      "video": null,
      "image": "https://images.animefansbase.com/artwork/md/2023/08/47176-64ddc49175454.jpeg",
      "postDate": "2023-08-17 06:56:18",
      "likes": 0,
      "comment": 0,
      "totalRepost": 0,
      "isLiked": false,
      "isRepost": 0,
      "commentPreview": null
    },
    {
      "categoryId": 8343,
      "id": 25489,
      "username": "@ralex_",
      "fullName": "Robin Alexander",
      "avatar": "https://images.animefansbase.com/avatar/r/ralex_65380.jpg",
      "video": null,
      "image": "https://images.animefansbase.com/artwork/md/2023/08/63235-64dd1401bb050.jpeg",
      "postDate": "2023-08-16 18:22:58",
      "likes": 2,
      "comment": 0,
      "totalRepost": 0,
      "isLiked": false,
      "isRepost": 0,
      "commentPreview": null
    },
    {
      "categoryId": 8342,
      "id": 25482,
      "username": "@art_lover",
      "fullName": "Jasmine ❤️",
      "avatar": "https://images.animefansbase.com/avatar/r/art_lover3167.jpg",
      "video": null,
      "image": "https://images.animefansbase.com/artwork/md/2023/08/11490-64dcdfd6ea7b0.jpeg",
      "postDate": "2023-08-16 14:40:24",
      "likes": 0,
      "comment": 0,
      "totalRepost": 0,
      "isLiked": false,
      "isRepost": 0,
      "commentPreview": null
    },
    {
      "categoryId": 8341,
      "id": 25480,
      "username": "@ralex_",
      "fullName": "Robin Alexander",
      "avatar": "https://images.animefansbase.com/avatar/r/ralex_65380.jpg",
      "video": null,
      "image": "https://images.animefansbase.com/artwork/md/2023/08/42035-64dc97bc6ed26.jpeg",
      "postDate": "2023-08-16 09:32:45",
      "likes": 1,
      "comment": 0,
      "totalRepost": 0,
      "isLiked": false,
      "isRepost": 0,
      "commentPreview": null
    },
    {
      "categoryId": 8340,
      "id": 25478,
      "username": "@art_lover",
      "fullName": "Jasmine ❤️",
      "avatar": "https://images.animefansbase.com/avatar/r/art_lover3167.jpg",
      "video": null,
      "image": "https://images.animefansbase.com/artwork/md/2023/08/67349-64dc6d2f2bd63.jpeg",
      "postDate": "2023-08-16 06:31:12",
      "likes": 2,
      "comment": 0,
      "totalRepost": 0,
      "isLiked": false,
      "isRepost": 0,
      "commentPreview": null
    },
    {
      "categoryId": 8339,
      "id": 25473,
      "username": "@ralex_",
      "fullName": "Robin Alexander",
      "avatar": "https://images.animefansbase.com/avatar/r/ralex_65380.jpg",
      "video": null,
      "image": "https://images.animefansbase.com/artwork/md/2023/08/44965-64dbcf2604654.jpeg",
      "postDate": "2023-08-15 19:16:55",
      "likes": 1,
      "comment": 0,
      "totalRepost": 0,
      "isLiked": false,
      "isRepost": 0,
      "commentPreview": null
    },
    {
      "categoryId": 8338,
      "id": 25471,
      "username": "@art_lover",
      "fullName": "Jasmine ❤️",
      "avatar": "https://images.animefansbase.com/avatar/r/art_lover3167.jpg",
      "video": null,
      "image": "https://images.animefansbase.com/artwork/md/2023/08/72818-64db8a4b09675.jpeg",
      "postDate": "2023-08-15 14:23:08",
      "likes": 3,
      "comment": 1,
      "totalRepost": 0,
      "isLiked": false,
      "isRepost": 0,
      "commentPreview": {
        "id": "527",
        "image": null,
        "avatar": "kristina1620.jpg",
        "fullName": "Anime fan ❤️❤️",
        "username": "@kristina",
        "postDate": "2023-08-15 15:26:24",
        "commentTxt": "Kawai desu ❤️❤️"
      }
    },
    {
      "categoryId": 8337,
      "id": 25460,
      "username": "@ralex_",
      "fullName": "Robin Alexander",
      "avatar": "https://images.animefansbase.com/avatar/r/ralex_65380.jpg",
      "video": null,
      "image": "https://images.animefansbase.com/artwork/md/2023/08/21288-64db4500e494d.jpg",
      "postDate": "2023-08-15 09:27:31",
      "likes": 2,
      "comment": 0,
      "totalRepost": 0,
      "isLiked": false,
      "isRepost": 0,
      "commentPreview": null
    },
    {
      "categoryId": 8336,
      "id": 25456,
      "username": "@art_lover",
      "fullName": "Jasmine ❤️",
      "avatar": "https://images.animefansbase.com/avatar/r/art_lover3167.jpg",
      "video": null,
      "image": "https://images.animefansbase.com/artwork/md/2023/08/58633-64db06c9f0b9a.jpeg",
      "postDate": "2023-08-15 05:02:03",
      "likes": 2,
      "comment": 0,
      "totalRepost": 0,
      "isLiked": false,
      "isRepost": 0,
      "commentPreview": null
    },
    {
      "categoryId": 8335,
      "id": 25448,
      "username": "@ralex_",
      "fullName": "Robin Alexander",
      "avatar": "https://images.animefansbase.com/avatar/r/ralex_65380.jpg",
      "video": null,
      "image": "https://images.animefansbase.com/artwork/md/2023/08/57981-64da6569bf64a.jpeg",
      "postDate": "2023-08-14 17:33:30",
      "likes": 2,
      "comment": 0,
      "totalRepost": 0,
      "isLiked": false,
      "isRepost": 0,
      "commentPreview": null
    },
    {
      "categoryId": 8334,
      "id": 25446,
      "username": "@art_lover",
      "fullName": "Jasmine ❤️",
      "avatar": "https://images.animefansbase.com/avatar/r/art_lover3167.jpg",
      "video": null,
      "image": "https://images.animefansbase.com/artwork/md/2023/08/83627-64da50dcda91a.jpeg",
      "postDate": "2023-08-14 16:05:50",
      "likes": 1,
      "comment": 0,
      "totalRepost": 0,
      "isLiked": false,
      "isRepost": 0,
      "commentPreview": null
    },
    {
      "categoryId": 8333,
      "id": 25442,
      "username": "@ralex_",
      "fullName": "Robin Alexander",
      "avatar": "https://images.animefansbase.com/avatar/r/ralex_65380.jpg",
      "video": null,
      "image": "https://images.animefansbase.com/artwork/md/2023/08/12381-64da124c3f1bb.jpg",
      "postDate": "2023-08-14 11:38:52",
      "likes": 0,
      "comment": 0,
      "totalRepost": 0,
      "isLiked": false,
      "isRepost": 0,
      "commentPreview": null
    },
    {
      "categoryId": 8332,
      "id": 25440,
      "username": "@art_lover",
      "fullName": "Jasmine ❤️",
      "avatar": "https://images.animefansbase.com/avatar/r/art_lover3167.jpg",
      "video": null,
      "image": "https://images.animefansbase.com/artwork/md/2023/08/10818-64d9d878adb9c.jpeg",
      "postDate": "2023-08-14 07:32:09",
      "likes": 0,
      "comment": 0,
      "totalRepost": 0,
      "isLiked": false,
      "isRepost": 0,
      "commentPreview": null
    }
  ]
}